LICENSE
README.md
setup.py
archivezip/__init__.py
banner/__init__.py
banner/sinontop_banner.py
codm/__init__.py
confighum.egg-info/PKG-INFO
confighum.egg-info/SOURCES.txt
confighum.egg-info/dependency_links.txt
confighum.egg-info/top_level.txt
configs/__init__.py
tools/__init__.py
tools/enc.py
tools/merge.py
tools/sep.py