Metadata-Version: 2.4
Name: confighum
Version: 0.3.5
Summary: A collection of sinontop utilities and configurations.
Author: Sintacs Ao
Author-email: adas334@gmail.com
Requires-Python: >=3.6
License-File: LICENSE
Dynamic: author
Dynamic: author-email
Dynamic: description
Dynamic: description-content-type
Dynamic: license-file
Dynamic: requires-python
Dynamic: summary
